accounts/__init__.py
accounts/admin.py
accounts/apps.py
accounts/forms.py
accounts/models.py
accounts/tests.py
accounts/token.py
accounts/urls.py
accounts/views.py
accounts/migrations/0001_initial.py
accounts/migrations/__init__.py
cloud/__init__.py
cloud/admin.py
cloud/apps.py
cloud/cart.py
cloud/models.py
cloud/tests.py
cloud/views.py
cloud/migrations/0001_initial.py
cloud/migrations/__init__.py
geolocation/__init__.py
geolocation/admin.py
geolocation/apps.py
geolocation/models.py
geolocation/tests.py
geolocation/views.py
geolocation/migrations/0001_initial.py
geolocation/migrations/__init__.py
stela_control/__init__.py
stela_control/admin.py
stela_control/apps.py
stela_control/cart.py
stela_control/context_processors.py
stela_control/cron.py
stela_control/forms.py
stela_control/functions.py
stela_control/models.py
stela_control/routers.py
stela_control/superfunctions.py
stela_control/tasks.py
stela_control/tests.py
stela_control/tokenize.py
stela_control/urls.py
stela_control/views.py
stela_control/locale/es/LC_MESSAGES/django.mo
stela_control/locale/es/LC_MESSAGES/django.po
stela_control/migrations/0001_initial.py
stela_control/migrations/0002_alter_billingrecipt_option_alter_company_business_and_more.py
stela_control/migrations/0002_remove_prosteladata_chatbox_and_more.py
stela_control/migrations/0003_prosteladata_avatar_alter_billingrecipt_option_and_more.py
stela_control/migrations/__init__.py
stela_control/templates/stela_control/base.html
stela_control/templates/stela_control/base_content.html
stela_control/templates/stela_control/base_list.html
stela_control/templates/stela_control/home.html
stela_control/templates/stela_control/index.html
stela_control/templates/stela_control/newcomer.html
stela_control/templates/stela_control/accounts/base.html
stela_control/templates/stela_control/accounts/registration/account_activation_email.html
stela_control/templates/stela_control/accounts/registration/activation_invalid.html
stela_business-0.1.13.dist-info/LICENSE
stela_business-0.1.13.dist-info/METADATA
stela_business-0.1.13.dist-info/WHEEL
stela_business-0.1.13.dist-info/top_level.txt
stela_business-0.1.13.dist-info/RECORD
