Metadata-Version: 2.1
Name: stela_business
Version: 0.1.13
Summary: All apps in one for business.
License: MIT
Classifier: Environment :: Web Environment
Classifier: Framework :: Django
Classifier: Programming Language :: Python :: 3
Classifier: License :: OSI Approved :: MIT License
Classifier: Operating System :: OS Independent
License-File: LICENSE
Requires-Dist: Babel
Requires-Dist: beautifulsoup4
Requires-Dist: bleach
Requires-Dist: boto3
Requires-Dist: cryptography
Requires-Dist: pycryptodome
Requires-Dist: Django
Requires-Dist: django-cities-light
Requires-Dist: django-ckeditor
Requires-Dist: django-crispy-forms
Requires-Dist: django-cron
Requires-Dist: django-environ
Requires-Dist: django-hosts
Requires-Dist: django-restframework
Requires-Dist: django-storages
Requires-Dist: google-api-python-client
Requires-Dist: facebook-business
Requires-Dist: gunicorn
Requires-Dist: jwt
Requires-Dist: openai
Requires-Dist: paypal-checkout-serversdk
Requires-Dist: paypalrestsdk
Requires-Dist: phonenumbers
Requires-Dist: crispy-bootstrap4
Requires-Dist: Pillow
Requires-Dist: python-amazon-paapi
Requires-Dist: stripe
Requires-Dist: psycopg2-binary
